{
  "volume": 10,
  "month": "October",
  "year": 1923,
  "total": 22,
  "ok": 20,
  "flagged": 2,
  "empty": 0,
  "records": [
    {
      "file": "October_Vol10_00_BOARD.txt",
      "body_len": 627,
      "article_words": 63,
      "words_in_ocr": 63,
      "pct_in_ocr": 1.0,
      "first_phrase_in_ocr": false,
      "status": "OK",
      "flags": [],
      "is_special": true,
      "remediation": null,
      "sample_not_in_ocr": []
    },
    {
      "file": "October_Vol10_00_CONTENTS.txt",
      "body_len": 578,
      "article_words": 51,
      "words_in_ocr": 51,
      "pct_in_ocr": 1.0,
      "first_phrase_in_ocr": false,
      "status": "OK",
      "flags": [],
      "is_special": true,
      "remediation": null,
      "sample_not_in_ocr": []
    },
    {
      "file": "October_Vol10_01_Frontispiece_The_Temple_at_Cardston,_Canada_Frontispiece.txt",
      "body_len": 602,
      "article_words": 73,
      "words_in_ocr": 73,
      "pct_in_ocr": 1.0,
      "first_phrase_in_ocr": false,
      "status": "OK",
      "flags": [],
      "is_special": false,
      "remediation": null,
      "sample_not_in_ocr": []
    },
    {
      "file": "October_Vol10_02_Poetry_A_Temple_in_Canada_(A_Poem)_Helen_Orgill.txt",
      "body_len": 78,
      "article_words": 9,
      "words_in_ocr": 9,
      "pct_in_ocr": 1.0,
      "first_phrase_in_ocr": false,
      "status": "FLAG",
      "flags": [
        "SHORT(78)"
      ],
      "is_special": false,
      "remediation": "manual_review",
      "sample_not_in_ocr": []
    },
    {
      "file": "October_Vol10_03_Article_The_Canada_Temple_Alice_Louise_Reynolds.txt",
      "body_len": 2403,
      "article_words": 178,
      "words_in_ocr": 178,
      "pct_in_ocr": 1.0,
      "first_phrase_in_ocr": true,
      "status": "OK",
      "flags": [],
      "is_special": false,
      "remediation": null,
      "sample_not_in_ocr": []
    },
    {
      "file": "October_Vol10_04_Article_President_Heber_J._Grant_(Portrait).txt",
      "body_len": 16380,
      "article_words": 645,
      "words_in_ocr": 645,
      "pct_in_ocr": 1.0,
      "first_phrase_in_ocr": false,
      "status": "OK",
      "flags": [],
      "is_special": false,
      "remediation": null,
      "sample_not_in_ocr": []
    },
    {
      "file": "October_Vol10_05a_Article_President_Grants_Dedicatory_Prayer.txt",
      "body_len": 16444,
      "article_words": 648,
      "words_in_ocr": 648,
      "pct_in_ocr": 1.0,
      "first_phrase_in_ocr": false,
      "status": "OK",
      "flags": [],
      "is_special": false,
      "remediation": null,
      "sample_not_in_ocr": []
    },
    {
      "file": "October_Vol10_06_Poetry_Now_is_the_Time_(Poem)_Annie_G._Lauritzen.txt",
      "body_len": 703,
      "article_words": 60,
      "words_in_ocr": 60,
      "pct_in_ocr": 1.0,
      "first_phrase_in_ocr": false,
      "status": "OK",
      "flags": [],
      "is_special": false,
      "remediation": null,
      "sample_not_in_ocr": []
    },
    {
      "file": "October_Vol10_07_Article_Ada_Louise_Comstock_(with_Portrait).txt",
      "body_len": 3303,
      "article_words": 183,
      "words_in_ocr": 183,
      "pct_in_ocr": 1.0,
      "first_phrase_in_ocr": true,
      "status": "OK",
      "flags": [],
      "is_special": false,
      "remediation": null,
      "sample_not_in_ocr": []
    },
    {
      "file": "October_Vol10_08a_Article_Mother_as_a_Teacher_of_Religion.txt",
      "body_len": 1576,
      "article_words": 145,
      "words_in_ocr": 145,
      "pct_in_ocr": 1.0,
      "first_phrase_in_ocr": false,
      "status": "OK",
      "flags": [],
      "is_special": false,
      "remediation": null,
      "sample_not_in_ocr": []
    },
    {
      "file": "October_Vol10_08b_Editorial_Editorial.txt",
      "body_len": 10975,
      "article_words": 672,
      "words_in_ocr": 672,
      "pct_in_ocr": 1.0,
      "first_phrase_in_ocr": false,
      "status": "OK",
      "flags": [],
      "is_special": false,
      "remediation": null,
      "sample_not_in_ocr": []
    },
    {
      "file": "October_Vol10_10_Poetry_The_Great_Teacher_(Poem)_Alfred_Osmond.txt",
      "body_len": 1588,
      "article_words": 158,
      "words_in_ocr": 158,
      "pct_in_ocr": 1.0,
      "first_phrase_in_ocr": true,
      "status": "OK",
      "flags": [],
      "is_special": false,
      "remediation": null,
      "sample_not_in_ocr": []
    },
    {
      "file": "October_Vol10_11_Article_Mrs._Harriet_Perry_Whiting_Alice_Louise_Reynolds.txt",
      "body_len": 5311,
      "article_words": 339,
      "words_in_ocr": 339,
      "pct_in_ocr": 1.0,
      "first_phrase_in_ocr": false,
      "status": "OK",
      "flags": [],
      "is_special": false,
      "remediation": null,
      "sample_not_in_ocr": []
    },
    {
      "file": "October_Vol10_12a_Current_Topics_Educational_Items.txt",
      "body_len": 5920,
      "article_words": 426,
      "words_in_ocr": 426,
      "pct_in_ocr": 1.0,
      "first_phrase_in_ocr": false,
      "status": "OK",
      "flags": [],
      "is_special": false,
      "remediation": null,
      "sample_not_in_ocr": []
    },
    {
      "file": "October_Vol10_13_Notes_from_Field_Notes_from_the_Field_Amy_Brown_Lyman.txt",
      "body_len": 9405,
      "article_words": 519,
      "words_in_ocr": 519,
      "pct_in_ocr": 1.0,
      "first_phrase_in_ocr": true,
      "status": "OK",
      "flags": [],
      "is_special": false,
      "remediation": null,
      "sample_not_in_ocr": []
    },
    {
      "file": "October_Vol10_14a_Article_The_Way_of_Parents.txt",
      "body_len": 873,
      "article_words": 98,
      "words_in_ocr": 98,
      "pct_in_ocr": 1.0,
      "first_phrase_in_ocr": false,
      "status": "OK",
      "flags": [],
      "is_special": false,
      "remediation": null,
      "sample_not_in_ocr": []
    },
    {
      "file": "October_Vol10_14b_Guide_Lessons_Guide_Lessons_for_December_-_Lesson_I_-_Theology_Lesson_-_Th.txt",
      "body_len": 6144,
      "article_words": 368,
      "words_in_ocr": 368,
      "pct_in_ocr": 1.0,
      "first_phrase_in_ocr": false,
      "status": "OK",
      "flags": [],
      "is_special": false,
      "remediation": null,
      "sample_not_in_ocr": []
    },
    {
      "file": "October_Vol10_14c_Guide_Lessons_Guide_Lessons_for_December_-_Lesson_II_-_Work_and_Business.txt",
      "body_len": 53,
      "article_words": 7,
      "words_in_ocr": 7,
      "pct_in_ocr": 1.0,
      "first_phrase_in_ocr": false,
      "status": "FLAG",
      "flags": [
        "SHORT(53)"
      ],
      "is_special": false,
      "remediation": "manual_review",
      "sample_not_in_ocr": []
    },
    {
      "file": "October_Vol10_14d_Guide_Lessons_Guide_Lessons_for_December_-_Lesson_III_-_Literature_-_Ralph.txt",
      "body_len": 8240,
      "article_words": 570,
      "words_in_ocr": 570,
      "pct_in_ocr": 1.0,
      "first_phrase_in_ocr": false,
      "status": "OK",
      "flags": [],
      "is_special": false,
      "remediation": null,
      "sample_not_in_ocr": []
    },
    {
      "file": "October_Vol10_14e_Guide_Lessons_Guide_Lessons_for_December_-_Lesson_IV_-_Social_Service_-_Th.txt",
      "body_len": 4828,
      "article_words": 316,
      "words_in_ocr": 316,
      "pct_in_ocr": 1.0,
      "first_phrase_in_ocr": false,
      "status": "OK",
      "flags": [],
      "is_special": false,
      "remediation": null,
      "sample_not_in_ocr": []
    },
    {
      "file": "October_Vol10_14f_Guide_Lessons_Teachers_Topic_for_December_-_Special_Significance_of_Christ.txt",
      "body_len": 526,
      "article_words": 58,
      "words_in_ocr": 58,
      "pct_in_ocr": 1.0,
      "first_phrase_in_ocr": false,
      "status": "OK",
      "flags": [],
      "is_special": false,
      "remediation": null,
      "sample_not_in_ocr": []
    },
    {
      "file": "October_Vol10_Misc.txt",
      "body_len": 7364,
      "article_words": 482,
      "words_in_ocr": 479,
      "pct_in_ocr": 0.9938,
      "first_phrase_in_ocr": false,
      "status": "OK",
      "flags": [],
      "is_special": true,
      "remediation": null,
      "sample_not_in_ocr": [
        "gap",
        "text",
        "uncovered"
      ]
    }
  ],
  "meta": {
    "ocr_file": "Vol10_No10_October_1923.txt",
    "ocr_chars": 118216,
    "ocr_unique_words": 3713,
    "contents_xref": {
      "entries_in_contents": 14,
      "matched": 13,
      "match_details": [
        {
          "title": "The Temple at Cardston, Canada Frontispiece",
          "page": null,
          "file": "October_Vol10_01_Frontispiece_The_Temple_at_Cardston,_Canada_Frontispiece.txt",
          "score": 1.0
        },
        {
          "title": "A Temple in Canada (A Poem) Helen Orgill",
          "page": 477,
          "file": "October_Vol10_02_Poetry_A_Temple_in_Canada_(A_Poem)_Helen_Orgill.txt",
          "score": 1.0
        },
        {
          "title": "The Canada Temple Alice Louise Reynolds",
          "page": 479,
          "file": "October_Vol10_03_Article_The_Canada_Temple_Alice_Louise_Reynolds.txt",
          "score": 1.0
        },
        {
          "title": "President Heber J. Grant (Portrait)",
          "page": 481,
          "file": "October_Vol10_04_Article_President_Heber_J._Grant_(Portrait).txt",
          "score": 1.0
        },
        {
          "title": "President Grant's Dedicatory Prayer",
          "page": 481,
          "file": "October_Vol10_05a_Article_President_Grants_Dedicatory_Prayer.txt",
          "score": 0.75
        },
        {
          "title": "Now is the Time (Poem) Annie G. Lauritzen",
          "page": 487,
          "file": "October_Vol10_06_Poetry_Now_is_the_Time_(Poem)_Annie_G._Lauritzen.txt",
          "score": 1.0
        },
        {
          "title": "Ada Louise Comstock (with Portrait)",
          "page": 489,
          "file": "October_Vol10_07_Article_Ada_Louise_Comstock_(with_Portrait).txt",
          "score": 1.0
        },
        {
          "title": "Mother as a Teacher of Religion John Quayle",
          "page": 490,
          "file": "October_Vol10_08a_Article_Mother_as_a_Teacher_of_Religion.txt",
          "score": 0.6
        },
        {
          "title": "The Great Teacher (Poem) Alfred Osmond",
          "page": 496,
          "file": "October_Vol10_10_Poetry_The_Great_Teacher_(Poem)_Alfred_Osmond.txt",
          "score": 1.0
        },
        {
          "title": "Mrs. Harriet Perry Whiting Alice Louise Reynolds",
          "page": 497,
          "file": "October_Vol10_11_Article_Mrs._Harriet_Perry_Whiting_Alice_Louise_Reynolds.txt",
          "score": 1.0
        },
        {
          "title": "Educational Items",
          "page": 499,
          "file": "October_Vol10_12a_Current_Topics_Educational_Items.txt",
          "score": 1.0
        },
        {
          "title": "Notes from the Field Amy Brown Lyman",
          "page": 501,
          "file": "October_Vol10_13_Notes_from_Field_Notes_from_the_Field_Amy_Brown_Lyman.txt",
          "score": 1.0
        },
        {
          "title": "The Way of Parents Strickland Gillilan",
          "page": 507,
          "file": "October_Vol10_14a_Article_The_Way_of_Parents.txt",
          "score": 0.5
        }
      ],
      "missing": [
        {
          "title": "Editorials",
          "page": 491
        }
      ],
      "extra_files": [
        "October_Vol10_08b_Editorial_Editorial.txt",
        "October_Vol10_14b_Guide_Lessons_Guide_Lessons_for_December_-_Lesson_I_-_Theology_Lesson_-_Th.txt",
        "October_Vol10_14c_Guide_Lessons_Guide_Lessons_for_December_-_Lesson_II_-_Work_and_Business.txt",
        "October_Vol10_14d_Guide_Lessons_Guide_Lessons_for_December_-_Lesson_III_-_Literature_-_Ralph.txt",
        "October_Vol10_14e_Guide_Lessons_Guide_Lessons_for_December_-_Lesson_IV_-_Social_Service_-_Th.txt",
        "October_Vol10_14f_Guide_Lessons_Teachers_Topic_for_December_-_Special_Significance_of_Christ.txt"
      ]
    }
  }
}